setup.py
src/graccarchive/__init__.py
src/graccarchive/graccarchive.py
src/graccarchive/unarchive.py
src/graccarchive.egg-info/PKG-INFO
src/graccarchive.egg-info/SOURCES.txt
src/graccarchive.egg-info/dependency_links.txt
src/graccarchive.egg-info/entry_points.txt
src/graccarchive.egg-info/requires.txt
src/graccarchive.egg-info/top_level.txt