Metadata-Version: 1.0
Name: graccarchive
Version: 1.6.0
Summary: GRACC Archive Agent
Home-page: https://opensciencegrid.github.io/gracc
Author: Derek Weitzel
Author-email: dweitzel@cse.unl.edu
License: UNKNOWN
Platform: UNKNOWN
